{"version":3,"kind":"Article","sha256":"a5792a86c3c22a1cb2ad2c0ec4b77abc8477a9eb33791c44e2745f3c3c8c458c","slug":"index-general","location":"/index_general.md","dependencies":[],"frontmatter":{"title":"Index des mots-clés","content_includes_title":false,"authors":[{"nameParsed":{"literal":"Gilles Nguyen Vien","given":"Gilles Nguyen","family":"Vien"},"name":"Gilles Nguyen Vien","affiliations":["Département de Physique, Université de Bretagne Occidentale"],"id":"contributors-Users\\GillO\\Documents\\Enseigt\\coursMQ1depotPriveJbook2-1-x\\myst-generated-uid-0"}],"license":{"content":{"id":"CC-BY-NC-ND-4.0","url":"https://creativecommons.org/licenses/by-nc-nd/4.0/","name":"Creative Commons Attribution Non Commercial No Derivatives 4.0 International","CC":true}},"affiliations":[{"id":"Département de Physique, Université de Bretagne Occidentale","name":"Département de Physique, Université de Bretagne Occidentale"}],"numbering":{"title":{"offset":1}},"exports":[{"format":"md","filename":"index_general.md","url":"https://ngAtUbo.github.io/MQ_test_interactif/build/index_general-0a12e55a99b58a6ca00eab6f3acba52e.md"}]},"mdast":{"type":"root","children":[{"type":"block","children":[{"type":"heading","depth":2,"position":{"start":{"line":3,"column":1},"end":{"line":3,"column":1}},"children":[{"type":"text","value":"Index","position":{"start":{"line":3,"column":1},"end":{"line":3,"column":1}},"key":"SX1x8eeZxc"}],"identifier":"index","label":"Index","html_id":"index","implicit":true,"key":"kpPUXxB3XU"},{"type":"block","children":[{"type":"definitionList","children":[{"type":"definitionTerm","children":[{"type":"text","value":"A","key":"mEsPVvd8h2"}],"label":"index-heading-a","identifier":"index-heading-a","html_id":"index-heading-a","key":"cMqr0BYFSG"},{"type":"definitionDescription","children":[{"type":"text","value":"amplitude de localisation:","key":"T1XhcAZIKc"},{"type":"text","value":" ","key":"gGSuH61j6N"},{"type":"crossReference","identifier":"index-vyikra2zy0","label":"index-vyIkra2zY0","children":[{"type":"text","value":"amplitude de localisation","key":"ZhgRm7ZxR3"}],"kind":"span","template":"Span","resolved":true,"html_id":"index-vyikra2zy0","remote":true,"url":"/chap6-etats-quantiques","dataUrl":"/chap6-etats-quantiques.json","key":"ux4QiqkHRa"},{"type":"list","children":[],"key":"iJI1YHSbCS"},{"type":"text","value":"amplitude de probabilité:","key":"KvYjZoA09h"},{"type":"text","value":" ","key":"yQBRlfYHmk"},{"type":"crossReference","identifier":"index-t37knne6se","label":"index-T37kNNE6Se","children":[{"type":"text","value":"amplitude de probabilité","key":"Z2wzqHWEuZ"}],"kind":"span","template":"Span","resolved":true,"html_id":"index-t37knne6se","remote":true,"url":"/chap5-mecanique-apetp","dataUrl":"/chap5-mecanique-apetp.json","key":"Tx3IaruJL1"},{"type":"list","children":[],"key":"vWyiODpXtw"},{"type":"text","value":"amplitude de probabilité de transition:","key":"lGcqtO4GvV"},{"type":"text","value":" ","key":"mJ5WuWMcG5"},{"type":"crossReference","identifier":"index-espdri9f1c","label":"index-esPDRi9F1C","children":[{"type":"text","value":"amplitude de probabilité de transition","key":"CIbG7dURjS"}],"kind":"span","template":"Span","resolved":true,"html_id":"index-espdri9f1c","remote":true,"url":"/chap5-mecanique-apetp","dataUrl":"/chap5-mecanique-apetp.json","key":"BtqTxQ5O3l"},{"type":"list","children":[],"key":"ajUbOnvrMZ"}],"key":"Dhc9U4d5vw"},{"type":"definitionTerm","children":[{"type":"text","value":"C","key":"hElrUkwidp"}],"label":"index-heading-c","identifier":"index-heading-c","html_id":"index-heading-c","key":"LUK49bKFap"},{"type":"definitionDescription","children":[{"type":"text","value":"cohérence:","key":"sEhu5N0pDY"},{"type":"text","value":" ","key":"WgDfDzQwRq"},{"type":"crossReference","identifier":"index-hhlrfsl3ri","label":"index-HhLrFSl3Ri","children":[{"type":"text","value":"cohérence","key":"geZyeRC9qs"}],"kind":"span","template":"Span","resolved":true,"html_id":"index-hhlrfsl3ri","remote":true,"url":"/chap2-ondulatoire-classique","dataUrl":"/chap2-ondulatoire-classique.json","key":"yVv8kSQGro"},{"type":"list","children":[],"key":"gDzuESbu3S"},{"type":"text","value":"commutateur:","key":"XLfcH0MddC"},{"type":"text","value":" ","key":"RvgtS7hBzI"},{"type":"crossReference","identifier":"index-cpzgnrebz8","label":"index-cpZgnREbz8","children":[{"type":"text","value":"commutateur","key":"uya1AASMfJ"}],"kind":"span","template":"Span","resolved":true,"html_id":"index-cpzgnrebz8","remote":true,"url":"/chap6-etats-quantiques","dataUrl":"/chap6-etats-quantiques.json","key":"nHaaisHQxa"},{"type":"list","children":[],"key":"vt07OV1N77"},{"type":"text","value":"compatibles:","key":"d7TeEvlW7B"},{"type":"text","value":" ","key":"LCxPklqxBt"},{"type":"crossReference","identifier":"index-ydtlvfaqdo","label":"index-ydTLvfAQDO","children":[{"type":"text","value":"compatibles","key":"UOcHq0RTs8"}],"kind":"span","template":"Span","resolved":true,"html_id":"index-ydtlvfaqdo","remote":true,"url":"/chap6-etats-quantiques","dataUrl":"/chap6-etats-quantiques.json","key":"JattmpQAsY"},{"type":"list","children":[],"key":"H4gzKelyFS"},{"type":"text","value":"constante de Planck:","key":"l6k7tG9pvp"},{"type":"text","value":" ","key":"P0a5XbDWtE"},{"type":"crossReference","identifier":"index-vnuysghwmc","label":"index-vNUysGHwMc","children":[{"type":"text","value":"constante de Planck","key":"S7K1trvq6x"}],"kind":"span","template":"Span","resolved":true,"html_id":"index-vnuysghwmc","remote":true,"url":"/chap3-lumiere","dataUrl":"/chap3-lumiere.json","key":"BEWAur0Ldu"},{"type":"list","children":[],"key":"R7JggGWtod"},{"type":"text","value":"constante du mouvement:","key":"AKUCLJDoI2"},{"type":"text","value":" ","key":"IQxpBoevbg"},{"type":"crossReference","identifier":"index-i2a8cmhem2","label":"index-i2a8CmHeM2","children":[{"type":"text","value":"constante du mouvement","key":"VwCt5TvvCl"}],"kind":"span","template":"Span","resolved":true,"html_id":"index-i2a8cmhem2","remote":true,"url":"/chap7-evolution-temporelle","dataUrl":"/chap7-evolution-temporelle.json","key":"Leg3WinMxM"},{"type":"list","children":[],"key":"cowXElUKL7"},{"type":"text","value":"célérité:","key":"jRiN7Oqqov"},{"type":"text","value":" ","key":"KQO7pLt2xN"},{"type":"crossReference","identifier":"index-sxcvbljes4","label":"index-sXcvblJeS4","children":[{"type":"text","value":"célérité","key":"krp7iFdJmD"}],"kind":"span","template":"Span","resolved":true,"html_id":"index-sxcvbljes4","remote":true,"url":"/chap2-ondulatoire-classique","dataUrl":"/chap2-ondulatoire-classique.json","key":"b0PZ7ZhhYX"},{"type":"list","children":[],"key":"E5WvN8dF8i"}],"key":"z5r17ub7Lc"},{"type":"definitionTerm","children":[{"type":"text","value":"D","key":"dcAu0agOhn"}],"label":"index-heading-d","identifier":"index-heading-d","html_id":"index-heading-d","key":"eCWlFDtVxC"},{"type":"definitionDescription","children":[{"type":"text","value":"diffraction:","key":"XLQa4ND7LS"},{"type":"text","value":" ","key":"rfoOmZwoeD"},{"type":"crossReference","identifier":"index-uc7xykvpye","label":"index-uC7XyKvpyE","children":[{"type":"text","value":"diffraction","key":"ohVd8BS4QI"}],"kind":"span","template":"Span","resolved":true,"html_id":"index-uc7xykvpye","remote":true,"url":"/chap4-fondements","dataUrl":"/chap4-fondements.json","key":"XefHRW3UIn"},{"type":"list","children":[],"key":"MWp3OOHSNC"},{"type":"text","value":"différence de marche:","key":"SFiDJxtGbb"},{"type":"text","value":" ","key":"vwMIou8SfY"},{"type":"crossReference","identifier":"index-agx30ivs6g","label":"index-AGX30IvS6g","children":[{"type":"text","value":"différence de marche","key":"VdemuVjBPl"}],"kind":"span","template":"Span","resolved":true,"html_id":"index-agx30ivs6g","remote":true,"url":"/chap2-ondulatoire-classique","dataUrl":"/chap2-ondulatoire-classique.json","key":"vN8O1H82rI"},{"type":"list","children":[],"key":"aEhnB1izyS"},{"type":"text","value":"dispersif:","key":"cP1LPQstHv"},{"type":"text","value":" ","key":"QeTr3fkHts"},{"type":"crossReference","identifier":"index-gezd9vzfje","label":"index-gEZd9VZFjE","children":[{"type":"text","value":"dispersif","key":"kI6yIMvRZ8"}],"kind":"span","template":"Span","resolved":true,"html_id":"index-gezd9vzfje","remote":true,"url":"/chap2-ondulatoire-classique","dataUrl":"/chap2-ondulatoire-classique.json","key":"Ex1vqklVGL"},{"type":"list","children":[],"key":"hh9k6Hk1i1"}],"key":"jWqnZYbJ1X"},{"type":"definitionTerm","children":[{"type":"text","value":"E","key":"JcfAik1e3n"}],"label":"index-heading-e","identifier":"index-heading-e","html_id":"index-heading-e","key":"kOzrvU4jN2"},{"type":"definitionDescription","children":[{"type":"text","value":"effet Compton:","key":"uDAJk0o2WY"},{"type":"text","value":" ","key":"MnmuDh43XC"},{"type":"crossReference","identifier":"index-jnqxykoby4","label":"index-jnqxykoBy4","children":[{"type":"text","value":"effet Compton","key":"Zd55EmTRQM"}],"kind":"span","template":"Span","resolved":true,"html_id":"index-jnqxykoby4","remote":true,"url":"/chap3-lumiere","dataUrl":"/chap3-lumiere.json","key":"LFTASGNeEt"},{"type":"list","children":[],"key":"HezajvIhHz"},{"type":"text","value":"effet photo électrique:","key":"XPN4bwJfcT"},{"type":"text","value":" ","key":"hPV6gZn6SM"},{"type":"crossReference","identifier":"index-ep6n6rfwba","label":"index-EP6N6Rfwba","children":[{"type":"text","value":"effet photo électrique","key":"GyPJWYNlv9"}],"kind":"span","template":"Span","resolved":true,"html_id":"index-ep6n6rfwba","remote":true,"url":"/chap3-lumiere","dataUrl":"/chap3-lumiere.json","key":"ucmH4Z5zsD"},{"type":"text","value":", ","key":"jmtx0gbwy8"},{"type":"crossReference","identifier":"index-bsgna2wp76","label":"index-BSGNA2Wp76","children":[{"type":"text","value":"effet photo électrique","key":"WpNHJ1wcv5"}],"kind":"span","template":"Span","resolved":true,"html_id":"index-bsgna2wp76","remote":true,"url":"/chap3-lumiere","dataUrl":"/chap3-lumiere.json","key":"UReUHYSOAc"},{"type":"list","children":[],"key":"rCdAXsWai2"},{"type":"text","value":"effet tunnel:","key":"TpjsEPKC1S"},{"type":"text","value":" ","key":"rr3IjFNb7R"},{"type":"crossReference","identifier":"index-senir2vxkn","label":"index-SENir2vxKN","children":[{"type":"text","value":"effet tunnel","key":"QresdsBq5c"}],"kind":"span","template":"Span","resolved":true,"html_id":"index-senir2vxkn","remote":true,"url":"/chap4-fondements","dataUrl":"/chap4-fondements.json","key":"zKKIuH8ana"},{"type":"list","children":[],"key":"hM65oVi7eU"},{"type":"text","value":"espace des états:","key":"D1R3Vy8RM5"},{"type":"text","value":" ","key":"b7FLbEqBfz"},{"type":"crossReference","identifier":"index-ukitbtzrvi","label":"index-uKiTBtzrVi","children":[{"type":"text","value":"espace des états","key":"KSQh6K2DeE"}],"kind":"span","template":"Span","resolved":true,"html_id":"index-ukitbtzrvi","remote":true,"url":"/chap6-etats-quantiques","dataUrl":"/chap6-etats-quantiques.json","key":"mbschqvNtR"},{"type":"list","children":[],"key":"F6ZOCRMR2e"},{"type":"text","value":"espace dual:","key":"eb9kMLXGg0"},{"type":"text","value":" ","key":"PNQ2DCVuIp"},{"type":"crossReference","identifier":"index-odvpqjb1f2","label":"index-oDVpQJb1F2","children":[{"type":"text","value":"espace dual","key":"ZrBzm1EycI"}],"kind":"span","template":"Span","resolved":true,"html_id":"index-odvpqjb1f2","remote":true,"url":"/chap6-etats-quantiques","dataUrl":"/chap6-etats-quantiques.json","key":"To0ZvRFFF6"},{"type":"list","children":[],"key":"IpwYsU7Ph1"},{"type":"text","value":"équation aux valeurs propres:","key":"YlPxHqbiCj"},{"type":"text","value":" ","key":"Ld6MiEE69E"},{"type":"crossReference","identifier":"index-vdazlqdshc","label":"index-VDAzlqdShc","children":[{"type":"text","value":"équation aux valeurs propres","key":"eFYzha1VBX"}],"kind":"span","template":"Span","resolved":true,"html_id":"index-vdazlqdshc","remote":true,"url":"/chap7-evolution-temporelle","dataUrl":"/chap7-evolution-temporelle.json","key":"f6MvXxrhz8"},{"type":"list","children":[],"key":"VUIYb6xxFn"},{"type":"text","value":"état lié:","key":"m2509xoHdu"},{"type":"text","value":" ","key":"gHnihNdkpP"},{"type":"crossReference","identifier":"index-wehlaeeini","label":"index-wehlaeeINI","children":[{"type":"text","value":"état lié","key":"zKwH2ttVrs"}],"kind":"span","template":"Span","resolved":true,"html_id":"index-wehlaeeini","remote":true,"url":"/chap6-etats-quantiques","dataUrl":"/chap6-etats-quantiques.json","key":"vq7zakWfno"},{"type":"list","children":[],"key":"Bi4AY78CCI"},{"type":"text","value":"état quantique:","key":"JRQTTAHkAg"},{"type":"text","value":" ","key":"i9gEuL5Su5"},{"type":"crossReference","identifier":"index-mexzxlejrb","label":"index-MEXZxLEJrB","children":[{"type":"text","value":"état quantique","key":"FUEeArOjr6"}],"kind":"span","template":"Span","resolved":true,"html_id":"index-mexzxlejrb","remote":true,"url":"/chap6-etats-quantiques","dataUrl":"/chap6-etats-quantiques.json","key":"Tj4etqlBL6"},{"type":"list","children":[],"key":"mOFKAliayc"},{"type":"text","value":"états stationnaires:","key":"HfiNHO5DKU"},{"type":"text","value":" ","key":"UUjaAVM3Wx"},{"type":"crossReference","identifier":"index-wnfzhrhjmr","label":"index-wNFZhRHJMR","children":[{"type":"text","value":"états stationnaires","key":"Xos23s6Lxy"}],"kind":"span","template":"Span","resolved":true,"html_id":"index-wnfzhrhjmr","remote":true,"url":"/chap7-evolution-temporelle","dataUrl":"/chap7-evolution-temporelle.json","key":"hTxm5ebP7z"},{"type":"list","children":[],"key":"LTTf7tnMVg"}],"key":"B5ZUz2U1HL"},{"type":"definitionTerm","children":[{"type":"text","value":"F","key":"LUfCQbtjL6"}],"label":"index-heading-f","identifier":"index-heading-f","html_id":"index-heading-f","key":"WALMWXs9kZ"},{"type":"definitionDescription","children":[{"type":"text","value":"Fonction d'onde de carré sommable:","key":"BoUB624CSx"},{"type":"text","value":" ","key":"RzX520osKO"},{"type":"crossReference","identifier":"index-tmsgguwqvb","label":"index-TMSGGUwqvB","children":[{"type":"text","value":"Fonction d'onde de carré sommable","key":"tg7qFTqppz"}],"kind":"span","template":"Span","resolved":true,"html_id":"index-tmsgguwqvb","remote":true,"url":"/chap6-etats-quantiques","dataUrl":"/chap6-etats-quantiques.json","key":"qcBfU9PGZV"},{"type":"list","children":[],"key":"WfLfXDCdYv"},{"type":"text","value":"facteur de phase:","key":"Vs625CNxnd"},{"type":"text","value":" ","key":"PJ1G8DE4go"},{"type":"crossReference","identifier":"index-hkuvkwrdjj","label":"index-hkuvKwRDjJ","children":[{"type":"text","value":"facteur de phase","key":"CHS4taWIJe"}],"kind":"span","template":"Span","resolved":true,"html_id":"index-hkuvkwrdjj","remote":true,"url":"/chap5-mecanique-apetp","dataUrl":"/chap5-mecanique-apetp.json","key":"iXtV0B1WOA"},{"type":"list","children":[],"key":"Q0TqTW2G8R"},{"type":"text","value":"fonction d’onde:","key":"P4NBGVavO9"},{"type":"text","value":" ","key":"ggwogwlA8k"},{"type":"crossReference","identifier":"index-etcmz771md","label":"index-eTCMZ771mD","children":[{"type":"text","value":"fonction d’onde","key":"AEsJEnDh9F"}],"kind":"span","template":"Span","resolved":true,"html_id":"index-etcmz771md","remote":true,"url":"/chap6-etats-quantiques","dataUrl":"/chap6-etats-quantiques.json","key":"Y3HD9wc59s"},{"type":"list","children":[],"key":"NO5cQU1m5D"},{"type":"text","value":"front d'onde:","key":"EYWAaCoaFK"},{"type":"text","value":" ","key":"ajnJhmlPQB"},{"type":"crossReference","identifier":"index-ey7iqqnamt","label":"index-ey7iQQnaMT","children":[{"type":"text","value":"front d'onde","key":"ZO3Jq9Pmzq"}],"kind":"span","template":"Span","resolved":true,"html_id":"index-ey7iqqnamt","remote":true,"url":"/chap2-ondulatoire-classique","dataUrl":"/chap2-ondulatoire-classique.json","key":"gJnVbrHTpj"},{"type":"list","children":[],"key":"cn9EnEeoqb"},{"type":"text","value":"fréquence:","key":"QufL2gvSqn"},{"type":"text","value":" ","key":"R00qZgTJ1J"},{"type":"crossReference","identifier":"index-nbf4nms8md","label":"index-nBf4Nms8MD","children":[{"type":"text","value":"fréquence","key":"CF5G3ifpU6"}],"kind":"span","template":"Span","resolved":true,"html_id":"index-nbf4nms8md","remote":true,"url":"/chap2-ondulatoire-classique","dataUrl":"/chap2-ondulatoire-classique.json","key":"V2F4AzZf1K"},{"type":"list","children":[],"key":"pflsQevLIw"}],"key":"PKznXpVShH"},{"type":"definitionTerm","children":[{"type":"text","value":"H","key":"BqxxNOkYYE"}],"label":"index-heading-h","identifier":"index-heading-h","html_id":"index-heading-h","key":"Zs5M6cyd6A"},{"type":"definitionDescription","children":[{"type":"text","value":"hermitique:","key":"AIdUvjHi5f"},{"type":"text","value":" ","key":"wm8fEP9T8U"},{"type":"crossReference","identifier":"index-q4g1uizgtv","label":"index-Q4g1uIzGtv","children":[{"type":"text","value":"hermitique","key":"GPDqWjVQwt"}],"kind":"span","template":"Span","resolved":true,"html_id":"index-q4g1uizgtv","remote":true,"url":"/chap6-etats-quantiques","dataUrl":"/chap6-etats-quantiques.json","key":"Nfz7pcSuTr"},{"type":"list","children":[],"key":"VUa5ma70DJ"}],"key":"hE9Hj9uAiQ"},{"type":"definitionTerm","children":[{"type":"text","value":"I","key":"yqmlSTynJW"}],"label":"index-heading-i","identifier":"index-heading-i","html_id":"index-heading-i","key":"lnod941va5"},{"type":"definitionDescription","children":[{"type":"text","value":"indice du milieu:","key":"Ep7WoLALNo"},{"type":"text","value":" ","key":"bwXkq8IPLt"},{"type":"crossReference","identifier":"index-izqq7peahr","label":"index-izqQ7Peahr","children":[{"type":"text","value":"indice du milieu","key":"BJGlnSDBNA"}],"kind":"span","template":"Span","resolved":true,"html_id":"index-izqq7peahr","remote":true,"url":"/chap2-ondulatoire-classique","dataUrl":"/chap2-ondulatoire-classique.json","key":"sgzMmZWXc9"},{"type":"list","children":[],"key":"dnxg7QRZgv"},{"type":"text","value":"inégalité d’Heisenberg:","key":"HStdELgbIM"},{"type":"text","value":" ","key":"FU1FFjKDYN"},{"type":"crossReference","identifier":"index-mqd2f8yntn","label":"index-mqD2f8YNTN","children":[{"type":"text","value":"inégalité d’Heisenberg","key":"sZ2OdAl824"}],"kind":"span","template":"Span","resolved":true,"html_id":"index-mqd2f8yntn","remote":true,"url":"/chap4-fondements","dataUrl":"/chap4-fondements.json","key":"GTPzMy8VbS"},{"type":"list","children":[],"key":"zvN3SEvUnI"},{"type":"text","value":"isotrope:","key":"kYb8s0MJOE"},{"type":"text","value":" ","key":"oMtRuvHe9Z"},{"type":"crossReference","identifier":"index-ddakfbyp60","label":"index-dDakfbyp60","children":[{"type":"text","value":"isotrope","key":"XKNKzke7BF"}],"kind":"span","template":"Span","resolved":true,"html_id":"index-ddakfbyp60","remote":true,"url":"/chap2-ondulatoire-classique","dataUrl":"/chap2-ondulatoire-classique.json","key":"wyyNsAxbvd"},{"type":"list","children":[],"key":"VxCEggGbYD"}],"key":"Rohp8zkcmA"},{"type":"definitionTerm","children":[{"type":"text","value":"L","key":"bhagSzDey0"}],"label":"index-heading-l","identifier":"index-heading-l","html_id":"index-heading-l","key":"cOtLTqiwAB"},{"type":"definitionDescription","children":[{"type":"text","value":"loi du déplacement de Wien:","key":"OIWfDlUYOd"},{"type":"text","value":" ","key":"OQV28st7Pb"},{"type":"crossReference","identifier":"index-sdsrnmkutl","label":"index-sDsRNmkUtL","children":[{"type":"text","value":"loi du déplacement de Wien","key":"koTQaKAnFm"}],"kind":"span","template":"Span","resolved":true,"html_id":"index-sdsrnmkutl","remote":true,"url":"/chap3-lumiere","dataUrl":"/chap3-lumiere.json","key":"diSNQyPu6x"},{"type":"list","children":[],"key":"LeMrlh0qnE"},{"type":"text","value":"longueur d'onde:","key":"XmO66PFD98"},{"type":"text","value":" ","key":"u7HsZuZtal"},{"type":"crossReference","identifier":"index-xrjvvksi45","label":"index-XrjVvKSi45","children":[{"type":"text","value":"longueur d'onde","key":"grNEbuz4yf"}],"kind":"span","template":"Span","resolved":true,"html_id":"index-xrjvvksi45","remote":true,"url":"/chap2-ondulatoire-classique","dataUrl":"/chap2-ondulatoire-classique.json","key":"Xx1ymwph4h"},{"type":"list","children":[],"key":"LvYF4xrqSN"}],"key":"k5ca52v89k"},{"type":"definitionTerm","children":[{"type":"text","value":"M","key":"Z8HZTfT6R5"}],"label":"index-heading-m","identifier":"index-heading-m","html_id":"index-heading-m","key":"hOcxQxpOF4"},{"type":"definitionDescription","children":[{"type":"text","value":"microscope de Heisenberg:","key":"N8nHatnf0f"},{"type":"text","value":" ","key":"cxwxDeOIZ0"},{"type":"crossReference","identifier":"index-ahozqmv65t","label":"index-aHOZqMv65t","children":[{"type":"text","value":"microscope de Heisenberg","key":"XqxoMJLnvN"}],"kind":"span","template":"Span","resolved":true,"html_id":"index-ahozqmv65t","remote":true,"url":"/chap4-fondements","dataUrl":"/chap4-fondements.json","key":"IIcvAyIW0g"},{"type":"list","children":[],"key":"NWt7iuw54j"},{"type":"text","value":"milieu:","key":"ycRGerreHa"},{"type":"text","value":" ","key":"Yfbb8KXStu"},{"type":"crossReference","identifier":"index-kwh0u0fszo","label":"index-kwh0U0fsZo","children":[{"type":"text","value":"milieu","key":"JSByJR5aK7"}],"kind":"span","template":"Span","resolved":true,"html_id":"index-kwh0u0fszo","remote":true,"url":"/chap2-ondulatoire-classique","dataUrl":"/chap2-ondulatoire-classique.json","key":"pV66Ezcqzg"},{"type":"list","children":[],"key":"shwPncErhP"}],"key":"Eu4I5Lx2iX"},{"type":"definitionTerm","children":[{"type":"text","value":"N","key":"FJVNkYDZ04"}],"label":"index-heading-n","identifier":"index-heading-n","html_id":"index-heading-n","key":"tBysJVgGp9"},{"type":"definitionDescription","children":[{"type":"text","value":"nombre d’onde:","key":"dofGodnHUL"},{"type":"text","value":" ","key":"iA92HIL6bz"},{"type":"crossReference","identifier":"index-d3cyns2jiy","label":"index-D3cYns2jIY","children":[{"type":"text","value":"nombre d’onde","key":"HGs0kE3x2j"}],"kind":"span","template":"Span","resolved":true,"html_id":"index-d3cyns2jiy","remote":true,"url":"/chap2-ondulatoire-classique","dataUrl":"/chap2-ondulatoire-classique.json","key":"cGaUHLi7oV"},{"type":"list","children":[],"key":"W4ItrYn2DM"}],"key":"esCSrdDHeI"},{"type":"definitionTerm","children":[{"type":"text","value":"O","key":"rRIb8Sjjac"}],"label":"index-heading-o","identifier":"index-heading-o","html_id":"index-heading-o","key":"jTP5JZzML5"},{"type":"definitionDescription","children":[{"type":"text","value":"observable:","key":"G0UeicEB3K"},{"type":"text","value":" ","key":"QZ7Hpv9sUP"},{"type":"crossReference","identifier":"index-uchjvamyzq","label":"index-UchJVAmyzQ","children":[{"type":"text","value":"observable","key":"S5BkJW0Fsb"}],"kind":"span","template":"Span","resolved":true,"html_id":"index-uchjvamyzq","remote":true,"url":"/chap6-etats-quantiques","dataUrl":"/chap6-etats-quantiques.json","key":"mbKcsDps70"},{"type":"list","children":[],"key":"l2pEWFFrG8"},{"type":"text","value":"observer effect:","key":"iUeSWOA3yo"},{"type":"text","value":" ","key":"ahFuG3x9PQ"},{"type":"crossReference","identifier":"index-jzb44bvbip","label":"index-jzb44BVBiP","children":[{"type":"text","value":"observer effect","key":"S8d43Zn3vS"}],"kind":"span","template":"Span","resolved":true,"html_id":"index-jzb44bvbip","remote":true,"url":"/chap4-fondements","dataUrl":"/chap4-fondements.json","key":"DYKJgORcav"},{"type":"list","children":[],"key":"hhg7nlRsWT"},{"type":"text","value":"onde longitudinale:","key":"uDTEWsxyWA"},{"type":"text","value":" ","key":"lprl6DRQJ8"},{"type":"crossReference","identifier":"index-cpdruthaaf","label":"index-CPdRUthAAf","children":[{"type":"text","value":"onde longitudinale","key":"DWERsA86jM"}],"kind":"span","template":"Span","resolved":true,"html_id":"index-cpdruthaaf","remote":true,"url":"/chap2-ondulatoire-classique","dataUrl":"/chap2-ondulatoire-classique.json","key":"PneHdubHkM"},{"type":"list","children":[],"key":"e9qx6VPWgx"},{"type":"text","value":"onde plane:","key":"qc7vPOueM1"},{"type":"text","value":" ","key":"F4xlI2pqOf"},{"type":"crossReference","identifier":"index-slsqnpyivi","label":"index-slsQNpYIVI","children":[{"type":"text","value":"onde plane","key":"GiRtKCdyKH"}],"kind":"span","template":"Span","resolved":true,"html_id":"index-slsqnpyivi","remote":true,"url":"/chap2-ondulatoire-classique","dataUrl":"/chap2-ondulatoire-classique.json","key":"UkyjO4I4fh"},{"type":"text","value":", ","key":"CFQOdahQNg"},{"type":"crossReference","identifier":"index-vf7pxpffmf","label":"index-VF7PxPffmf","children":[{"type":"text","value":"onde plane","key":"O4f9X1pi7I"}],"kind":"span","template":"Span","resolved":true,"html_id":"index-vf7pxpffmf","remote":true,"url":"/chap2-ondulatoire-classique","dataUrl":"/chap2-ondulatoire-classique.json","key":"CmF08u9tzF"},{"type":"text","value":", ","key":"k7SQ9tG8ss"},{"type":"crossReference","identifier":"index-hnkrivmsfv","label":"index-hnKRIVMSfv","children":[{"type":"text","value":"onde plane","key":"BpNXlzR6yB"}],"kind":"span","template":"Span","resolved":true,"html_id":"index-hnkrivmsfv","remote":true,"url":"/chap2-ondulatoire-classique","dataUrl":"/chap2-ondulatoire-classique.json","key":"J1UNGnI9UP"},{"type":"list","children":[],"key":"e5ReQ0eu4X"},{"type":"text","value":"onde sphérique:","key":"RhyH8BD3u9"},{"type":"text","value":" ","key":"TMd1hU47LD"},{"type":"crossReference","identifier":"index-gmgnpqnqmp","label":"index-GMgNPQnQMp","children":[{"type":"text","value":"onde sphérique","key":"qtQ8RqanMO"}],"kind":"span","template":"Span","resolved":true,"html_id":"index-gmgnpqnqmp","remote":true,"url":"/chap2-ondulatoire-classique","dataUrl":"/chap2-ondulatoire-classique.json","key":"FbPs18PAdU"},{"type":"list","children":[],"key":"o0U7ut6nJX"},{"type":"text","value":"onde transversale:","key":"AadE4wdpRD"},{"type":"text","value":" ","key":"ubPQZmoSC5"},{"type":"crossReference","identifier":"index-mutkykue0k","label":"index-mUTKykuE0k","children":[{"type":"text","value":"onde transversale","key":"bGjEo5I08i"}],"kind":"span","template":"Span","resolved":true,"html_id":"index-mutkykue0k","remote":true,"url":"/chap2-ondulatoire-classique","dataUrl":"/chap2-ondulatoire-classique.json","key":"zs2WaswEPM"},{"type":"list","children":[],"key":"UIZ2BY9hSi"},{"type":"text","value":"opérateur hamiltonien:","key":"WI5vHkhTiq"},{"type":"text","value":" ","key":"klNplSJmE6"},{"type":"crossReference","identifier":"index-wbqgwazluj","label":"index-WBQgWaZluJ","children":[{"type":"text","value":"opérateur hamiltonien","key":"atoCVbSISU"}],"kind":"span","template":"Span","resolved":true,"html_id":"index-wbqgwazluj","remote":true,"url":"/chap7-evolution-temporelle","dataUrl":"/chap7-evolution-temporelle.json","key":"W6jeTtNc0H"},{"type":"list","children":[],"key":"vv1MdHxS5N"}],"key":"i2BxobnL50"},{"type":"definitionTerm","children":[{"type":"text","value":"P","key":"bMeU6qfwey"}],"label":"index-heading-p","identifier":"index-heading-p","html_id":"index-heading-p","key":"haQhOR19Wf"},{"type":"definitionDescription","children":[{"type":"text","value":"paquets d'onde:","key":"AlZUucUmVs"},{"type":"text","value":" ","key":"k1VIFClgHB"},{"type":"crossReference","identifier":"index-fvt5qqenhv","label":"index-Fvt5qqeNHV","children":[{"type":"text","value":"paquets d'onde","key":"AmkBRlASWE"}],"kind":"span","template":"Span","resolved":true,"html_id":"index-fvt5qqenhv","remote":true,"url":"/chap4-fondements","dataUrl":"/chap4-fondements.json","key":"AU4VlRL41z"},{"type":"list","children":[],"key":"CrPP0mzVzz"},{"type":"text","value":"plan de polarisation:","key":"JTjObCKkDB"},{"type":"text","value":" ","key":"NEcEOgu2bY"},{"type":"crossReference","identifier":"index-jjl9e79fkp","label":"index-JJl9E79FKP","children":[{"type":"text","value":"plan de polarisation","key":"XcT5YOVb1L"}],"kind":"span","template":"Span","resolved":true,"html_id":"index-jjl9e79fkp","remote":true,"url":"/chap2-ondulatoire-classique","dataUrl":"/chap2-ondulatoire-classique.json","key":"gzUPIQUhVd"},{"type":"list","children":[],"key":"ZwAfDJ1kTw"},{"type":"text","value":"principe de Fermat:","key":"GFcRUc7qec"},{"type":"text","value":" ","key":"Q5WiGH2z5y"},{"type":"crossReference","identifier":"index-cf9o46wkbh","label":"index-cf9O46Wkbh","children":[{"type":"text","value":"principe de Fermat","key":"Oz8dF5GTYf"}],"kind":"span","template":"Span","resolved":true,"html_id":"index-cf9o46wkbh","remote":true,"url":"/chap3-lumiere","dataUrl":"/chap3-lumiere.json","key":"MPNats9vIM"},{"type":"list","children":[],"key":"gfmdMFjpEN"},{"type":"text","value":"principe de superposition:","key":"MbD4Y28L8A"},{"type":"text","value":" ","key":"QTf3ppdbSv"},{"type":"crossReference","identifier":"index-wgnuiesenq","label":"index-WgNuieseNQ","children":[{"type":"text","value":"principe de superposition","key":"y4tOgX5QnJ"}],"kind":"span","template":"Span","resolved":true,"html_id":"index-wgnuiesenq","remote":true,"url":"/chap2-ondulatoire-classique","dataUrl":"/chap2-ondulatoire-classique.json","key":"QbLpHvoNrc"},{"type":"list","children":[],"key":"kQ18k084wM"},{"type":"text","value":"principe de superposition des amplitudes:","key":"YFE2MnIgCS"},{"type":"text","value":" ","key":"YIAEmBVJjQ"},{"type":"crossReference","identifier":"index-plme7sosl4","label":"index-pLMe7sOsL4","children":[{"type":"text","value":"principe de superposition des amplitudes","key":"KETzladSe8"}],"kind":"span","template":"Span","resolved":true,"html_id":"index-plme7sosl4","remote":true,"url":"/chap5-mecanique-apetp","dataUrl":"/chap5-mecanique-apetp.json","key":"ar3UD5JWS5"},{"type":"list","children":[],"key":"Y1UUaK0mVd"},{"type":"text","value":"propagation:","key":"Nor62x1Eqp"},{"type":"text","value":" ","key":"qlMP0zSZFE"},{"type":"crossReference","identifier":"index-gznzixnmpo","label":"index-GZNZIxNmpO","children":[{"type":"text","value":"propagation","key":"mLop7iTDaO"}],"kind":"span","template":"Span","resolved":true,"html_id":"index-gznzixnmpo","remote":true,"url":"/chap2-ondulatoire-classique","dataUrl":"/chap2-ondulatoire-classique.json","key":"r21pcGnKpY"},{"type":"list","children":[],"key":"yyn7WQVLBw"},{"type":"text","value":"pulsation:","key":"CE61EgJJ5y"},{"type":"text","value":" ","key":"M918YPL1dT"},{"type":"crossReference","identifier":"index-n4n59rmtmt","label":"index-n4n59RmTmT","children":[{"type":"text","value":"pulsation","key":"PYPNa3kxHu"}],"kind":"span","template":"Span","resolved":true,"html_id":"index-n4n59rmtmt","remote":true,"url":"/chap2-ondulatoire-classique","dataUrl":"/chap2-ondulatoire-classique.json","key":"xSD1kLFOQi"},{"type":"list","children":[],"key":"qzifNC2vFn"},{"type":"text","value":"période:","key":"OGEAKb8GT7"},{"type":"text","value":" ","key":"l8qy7iDR45"},{"type":"crossReference","identifier":"index-pveqfhyoai","label":"index-PVEQFHyoAI","children":[{"type":"text","value":"période","key":"szLjqngRfB"}],"kind":"span","template":"Span","resolved":true,"html_id":"index-pveqfhyoai","remote":true,"url":"/chap2-ondulatoire-classique","dataUrl":"/chap2-ondulatoire-classique.json","key":"rCkg3u1iMr"},{"type":"list","children":[],"key":"KasmYma0FN"},{"type":"text","value":"périodicité:","key":"u0AXV8Q4m1"},{"type":"text","value":" ","key":"fiFxNeMhLS"},{"type":"crossReference","identifier":"index-nn2pnt9n8b","label":"index-nn2pnt9n8B","children":[{"type":"text","value":"périodicité","key":"FwMMjNVxeT"}],"kind":"span","template":"Span","resolved":true,"html_id":"index-nn2pnt9n8b","remote":true,"url":"/chap2-ondulatoire-classique","dataUrl":"/chap2-ondulatoire-classique.json","key":"tknrUUlfLW"},{"type":"list","children":[],"key":"Jr3i10hTfm"}],"key":"XeJueZak2H"},{"type":"definitionTerm","children":[{"type":"text","value":"Q","key":"RQYmsDzViX"}],"label":"index-heading-q","identifier":"index-heading-q","html_id":"index-heading-q","key":"Rd8jEzhSH0"},{"type":"definitionDescription","children":[{"type":"text","value":"quanta:","key":"oTzHqUJcmq"},{"type":"text","value":" ","key":"M9VFHc3DAV"},{"type":"crossReference","identifier":"index-e7v1bztnw5","label":"index-e7v1BzTNw5","children":[{"type":"text","value":"quanta","key":"K0zX0IrlET"}],"kind":"span","template":"Span","resolved":true,"html_id":"index-e7v1bztnw5","remote":true,"url":"/chap3-lumiere","dataUrl":"/chap3-lumiere.json","key":"A516vlr9X4"},{"type":"list","children":[],"key":"Q3dEiyaiUi"},{"type":"text","value":"quantons:","key":"VqCwjUnLd8"},{"type":"text","value":" ","key":"wU7pYJeVnf"},{"type":"crossReference","identifier":"index-nutd12ubpc","label":"index-NUTd12ubpc","children":[{"type":"text","value":"quantons","key":"rCvT1IJwAU"}],"kind":"span","template":"Span","resolved":true,"html_id":"index-nutd12ubpc","remote":true,"url":"/chap4-fondements","dataUrl":"/chap4-fondements.json","key":"WGxwUcYuVJ"},{"type":"list","children":[],"key":"Dgu91jSPiE"},{"type":"text","value":"quantum:","key":"DCeIjtZiRQ"},{"type":"text","value":" ","key":"Sjz9wLsI9Q"},{"type":"crossReference","identifier":"index-mdn0v6vhog","label":"index-mDn0v6vHoG","children":[{"type":"text","value":"quantum","key":"e9dHzJtCWB"}],"kind":"span","template":"Span","resolved":true,"html_id":"index-mdn0v6vhog","remote":true,"url":"/chap1-introduction","dataUrl":"/chap1-introduction.json","key":"Pi15iViObq"},{"type":"list","children":[],"key":"QUu9NK2ayt"}],"key":"YTzjkHTTuI"},{"type":"definitionTerm","children":[{"type":"text","value":"R","key":"NooqUUELoF"}],"label":"index-heading-r","identifier":"index-heading-r","html_id":"index-heading-r","key":"WDnK4GywBV"},{"type":"definitionDescription","children":[{"type":"text","value":"rayon lumineux:","key":"MWRXWX7jcV"},{"type":"text","value":" ","key":"H3AoweI70C"},{"type":"crossReference","identifier":"index-buaxutozgy","label":"index-bUAxUTOzGY","children":[{"type":"text","value":"rayon lumineux","key":"H8LHlDGPsA"}],"kind":"span","template":"Span","resolved":true,"html_id":"index-buaxutozgy","remote":true,"url":"/chap3-lumiere","dataUrl":"/chap3-lumiere.json","key":"LCHNZnkYkC"},{"type":"list","children":[],"key":"OSshRFbGGQ"},{"type":"text","value":"rayonnement du corps noir:","key":"xAvAVXAiE1"},{"type":"text","value":" ","key":"ABpvdpLxuF"},{"type":"crossReference","identifier":"index-gglsgsjjjc","label":"index-gGLsGsjjjc","children":[{"type":"text","value":"rayonnement du corps noir","key":"sOgfbq4hzH"}],"kind":"span","template":"Span","resolved":true,"html_id":"index-gglsgsjjjc","remote":true,"url":"/chap3-lumiere","dataUrl":"/chap3-lumiere.json","key":"OG596f1z69"},{"type":"list","children":[],"key":"Oexsq7jnsB"},{"type":"text","value":"rectiligne:","key":"MLKJjUUjrx"},{"type":"text","value":" ","key":"hX6aAh54RP"},{"type":"crossReference","identifier":"index-ajiv6t4ph3","label":"index-Ajiv6T4Ph3","children":[{"type":"text","value":"rectiligne","key":"ZYhKFsiGAX"}],"kind":"span","template":"Span","resolved":true,"html_id":"index-ajiv6t4ph3","remote":true,"url":"/chap3-lumiere","dataUrl":"/chap3-lumiere.json","key":"Rp6UZGvpFa"},{"type":"list","children":[],"key":"LNAkUg82nV"},{"type":"text","value":"relation de fermeture:","key":"DkX3ndEQNB"},{"type":"text","value":" ","key":"LVirBjVQSI"},{"type":"crossReference","identifier":"index-jrsucboona","label":"index-jrsucbOOna","children":[{"type":"text","value":"relation de fermeture","key":"nOkJGluwVw"}],"kind":"span","template":"Span","resolved":true,"html_id":"index-jrsucboona","remote":true,"url":"/chap6-etats-quantiques","dataUrl":"/chap6-etats-quantiques.json","key":"HgPGwGpz99"},{"type":"list","children":[],"key":"QHY68DCUta"}],"key":"tW7nBmO17T"},{"type":"definitionTerm","children":[{"type":"text","value":"S","key":"iwbDjMOQpv"}],"label":"index-heading-s","identifier":"index-heading-s","html_id":"index-heading-s","key":"iDgeUOIAjq"},{"type":"definitionDescription","children":[{"type":"text","value":"scintillation:","key":"banjvan0XK"},{"type":"text","value":" ","key":"TX40AsAPN3"},{"type":"crossReference","identifier":"index-xmp5aliv0m","label":"index-xmP5alIV0M","children":[{"type":"text","value":"scintillation","key":"Mp2GHTiJZn"}],"kind":"span","template":"Span","resolved":true,"html_id":"index-xmp5aliv0m","remote":true,"url":"/chap3-lumiere","dataUrl":"/chap3-lumiere.json","key":"mQF3iFVmdt"},{"type":"list","children":[],"key":"mmvzmDEsC9"},{"type":"text","value":"sources synchrones:","key":"tbM28wXnyZ"},{"type":"text","value":" ","key":"JVR5L8utIC"},{"type":"crossReference","identifier":"index-s6dcgybezn","label":"index-S6DCGYbEzn","children":[{"type":"text","value":"sources synchrones","key":"qFoRpmOLbF"}],"kind":"span","template":"Span","resolved":true,"html_id":"index-s6dcgybezn","remote":true,"url":"/chap2-ondulatoire-classique","dataUrl":"/chap2-ondulatoire-classique.json","key":"e39JM0JzeT"},{"type":"list","children":[],"key":"YgP6mh44O7"},{"type":"text","value":"superposition linéaire d'états:","key":"CLUa9VxsJL"},{"type":"text","value":" ","key":"u6m3kwuwU5"},{"type":"crossReference","identifier":"index-ag74mi6udd","label":"index-ag74mi6udd","children":[{"type":"text","value":"superposition linéaire d'états","key":"sfxEsHHUhv"}],"kind":"span","template":"Span","resolved":true,"html_id":"index-ag74mi6udd","remote":true,"url":"/chap6-etats-quantiques","dataUrl":"/chap6-etats-quantiques.json","key":"jL0TQlbnRA"},{"type":"list","children":[],"key":"Q4a9m9E4Zk"},{"type":"text","value":"surface d'onde:","key":"ysyoW6Xqpw"},{"type":"text","value":" ","key":"JxIPohhetR"},{"type":"crossReference","identifier":"index-zblry9j3um","label":"index-ZBLRY9j3um","children":[{"type":"text","value":"surface d'onde","key":"pgnrgdIwae"}],"kind":"span","template":"Span","resolved":true,"html_id":"index-zblry9j3um","remote":true,"url":"/chap2-ondulatoire-classique","dataUrl":"/chap2-ondulatoire-classique.json","key":"cIVQBgz8FR"},{"type":"list","children":[],"key":"WBYDFiqLPv"},{"type":"text","value":"série de fourier:","key":"L3MAicxyR4"},{"type":"text","value":" ","key":"NCCFzaCl50"},{"type":"crossReference","identifier":"index-sxsktjr9c6","label":"index-SxsKTjR9c6","children":[{"type":"text","value":"série de fourier","key":"epIu3LzTXk"}],"kind":"span","template":"Span","resolved":true,"html_id":"index-sxsktjr9c6","remote":true,"url":"/chap2-ondulatoire-classique","dataUrl":"/chap2-ondulatoire-classique.json","key":"fbCEZDghts"},{"type":"list","children":[],"key":"NYAGxHJysL"}],"key":"ZPOk7n2NtZ"},{"type":"definitionTerm","children":[{"type":"text","value":"T","key":"XjpemU37K0"}],"label":"index-heading-t","identifier":"index-heading-t","html_id":"index-heading-t","key":"i6OkQdl6cy"},{"type":"definitionDescription","children":[{"type":"text","value":"temps de réponse:","key":"hDiB4C4WRs"},{"type":"text","value":" ","key":"oeW8hM4zEd"},{"type":"crossReference","identifier":"index-jmpjgzybdi","label":"index-JmPjGzybdi","children":[{"type":"text","value":"temps de réponse","key":"yfiwFTZsZv"}],"kind":"span","template":"Span","resolved":true,"html_id":"index-jmpjgzybdi","remote":true,"url":"/chap2-ondulatoire-classique","dataUrl":"/chap2-ondulatoire-classique.json","key":"kcfHug3bYC"},{"type":"list","children":[],"key":"Yk4DacFmuk"},{"type":"text","value":"train d’onde:","key":"EACj5WoZuC"},{"type":"text","value":" ","key":"pIX822L21d"},{"type":"crossReference","identifier":"index-ldptlxagtn","label":"index-ldPtLXagtN","children":[{"type":"text","value":"train d’onde","key":"xCyETjmYeA"}],"kind":"span","template":"Span","resolved":true,"html_id":"index-ldptlxagtn","remote":true,"url":"/chap2-ondulatoire-classique","dataUrl":"/chap2-ondulatoire-classique.json","key":"LrF9npVHqo"},{"type":"list","children":[],"key":"tXsCRLOelf"},{"type":"text","value":"transformée de fourier:","key":"E543d3Yh9c"},{"type":"text","value":" ","key":"zkvyUg3LoH"},{"type":"crossReference","identifier":"index-te7ytxkvxi","label":"index-tE7YtxKVxi","children":[{"type":"text","value":"transformée de fourier","key":"jirUjNdaeh"}],"kind":"span","template":"Span","resolved":true,"html_id":"index-te7ytxkvxi","remote":true,"url":"/chap2-ondulatoire-classique","dataUrl":"/chap2-ondulatoire-classique.json","key":"lckQ3mlve7"},{"type":"list","children":[],"key":"ykn7nlhO3J"}],"key":"d8P7NPsnoZ"},{"type":"definitionTerm","children":[{"type":"text","value":"V","key":"mKggc244Zp"}],"label":"index-heading-v","identifier":"index-heading-v","html_id":"index-heading-v","key":"Jc5tGa8H6C"},{"type":"definitionDescription","children":[{"type":"text","value":"vecteur bra:","key":"JQz163S77F"},{"type":"text","value":" ","key":"DtNmkrw45g"},{"type":"crossReference","identifier":"index-zeckgh1qfv","label":"index-zEckGH1QfV","children":[{"type":"text","value":"vecteur bra","key":"X1OJwYHL5L"}],"kind":"span","template":"Span","resolved":true,"html_id":"index-zeckgh1qfv","remote":true,"url":"/chap6-etats-quantiques","dataUrl":"/chap6-etats-quantiques.json","key":"jhSNMWvWr0"},{"type":"list","children":[],"key":"NlOAOOcARI"},{"type":"text","value":"vecteur ket:","key":"uVwtaCRE4U"},{"type":"text","value":" ","key":"IwgQRQGALJ"},{"type":"crossReference","identifier":"index-qlctspwyui","label":"index-QLctSPwyui","children":[{"type":"text","value":"vecteur ket","key":"zH2qivhV5B"}],"kind":"span","template":"Span","resolved":true,"html_id":"index-qlctspwyui","remote":true,"url":"/chap6-etats-quantiques","dataUrl":"/chap6-etats-quantiques.json","key":"WH38jYNGM5"},{"type":"list","children":[],"key":"oXZ1DvQwyY"},{"type":"text","value":"vibration:","key":"NqvowHF5GH"},{"type":"text","value":" ","key":"JPUBrZb9Gh"},{"type":"crossReference","identifier":"index-ohidltddun","label":"index-oHIDlTDdUN","children":[{"type":"text","value":"vibration","key":"eaY5M1KDJL"}],"kind":"span","template":"Span","resolved":true,"html_id":"index-ohidltddun","remote":true,"url":"/chap2-ondulatoire-classique","dataUrl":"/chap2-ondulatoire-classique.json","key":"ySGK0yybyZ"},{"type":"list","children":[],"key":"eSocUv9rom"},{"type":"text","value":"vitesse de groupe:","key":"vyfblKaSwC"},{"type":"text","value":" ","key":"OuT58E6OQm"},{"type":"crossReference","identifier":"index-k88ffkuldb","label":"index-k88FfkUldb","children":[{"type":"text","value":"vitesse de groupe","key":"zck3LVjkJM"}],"kind":"span","template":"Span","resolved":true,"html_id":"index-k88ffkuldb","remote":true,"url":"/chap4-fondements","dataUrl":"/chap4-fondements.json","key":"Y0SrNVxRRZ"},{"type":"list","children":[],"key":"agDMzlIMO7"},{"type":"text","value":"vitesse de phase:","key":"S2OWuuTbzS"},{"type":"text","value":" ","key":"SNBplFQDyu"},{"type":"crossReference","identifier":"index-ndj0jbapnq","label":"index-nDJ0jBaPNq","children":[{"type":"text","value":"vitesse de phase","key":"akc7ijpZk8"}],"kind":"span","template":"Span","resolved":true,"html_id":"index-ndj0jbapnq","remote":true,"url":"/chap2-ondulatoire-classique","dataUrl":"/chap2-ondulatoire-classique.json","key":"z45juKGbXK"},{"type":"text","value":", ","key":"G4Eg8TCWog"},{"type":"crossReference","identifier":"index-rgkc7demah","label":"index-RGkc7DEmah","children":[{"type":"text","value":"vitesse de phase","key":"mpvzva3ETW"}],"kind":"span","template":"Span","resolved":true,"html_id":"index-rgkc7demah","remote":true,"url":"/chap2-ondulatoire-classique","dataUrl":"/chap2-ondulatoire-classique.json","key":"WSeWqvRmGx"},{"type":"list","children":[],"key":"pDznNkYc1o"}],"key":"SfbYkGwHBL"}],"key":"xdHJN9sfKI"}],"data":{"part":"index"},"key":"D2nU6vPjCC"}],"key":"Jiawn68FbZ"}],"key":"C1OXUiGus4"},"references":{"cite":{"order":[],"data":{}}},"footer":{"navigation":{"prev":{"title":"Opérateur d'évolution et équation de Schrödinger","url":"/chap7-evolution-temporelle","group":"Déployer le plan du cours"}}},"domain":"http://localhost:3000"}