{"version":3,"kind":"Article","sha256":"f5467640426376a4d70b8cd7f19910f7fc0c47a5508fcd36598d2ab49d29d6c9","slug":"index","location":"/coursMQ1.md","dependencies":[],"frontmatter":{"title":"INTRODUCTION A LA MECANIQUE QUANTIQUE","content_includes_title":false,"authors":[{"nameParsed":{"literal":"Gilles Nguyen Vien","given":"Gilles Nguyen","family":"Vien"},"name":"Gilles Nguyen Vien","id":"contributors-Users\\GillO\\Documents\\Enseigt\\coursMQ1depotPriveJbook2-1-x\\myst-generated-uid-0"}],"thumbnail":"/MQ_test_interactif/build/image1-eacb2516e5d702d9415d572961a06429.png","exports":[{"format":"md","filename":"coursMQ1.md","url":"/MQ_test_interactif/build/coursMQ1-ea401fff5ae506a295cd972a25451fcf.md"}]},"mdast":{"type":"root","children":[{"type":"block","children":[{"type":"paragraph","position":{"start":{"line":3,"column":1},"end":{"line":3,"column":1}},"children":[{"type":"text","value":"par ","position":{"start":{"line":3,"column":1},"end":{"line":3,"column":1}},"key":"rmHRjfA20J"},{"type":"strong","position":{"start":{"line":3,"column":1},"end":{"line":3,"column":1}},"children":[{"type":"text","value":"Gilles NGUYEN VIEN","position":{"start":{"line":3,"column":1},"end":{"line":3,"column":1}},"key":"hBvMglvZf6"}],"key":"EyRFrPXmBr"}],"key":"NBoB94yvBd"},{"type":"container","kind":"figure","children":[{"type":"image","url":"/MQ_test_interactif/build/image1-eacb2516e5d702d9415d572961a06429.png","width":"20%","key":"C8AXlEymK7","urlSource":"media/image1.png"}],"label":"fig-logoUBO","identifier":"fig-logoubo","enumerator":"1","html_id":"fig-logoubo","key":"xAf7SvebON"},{"type":"admonition","kind":"important","children":[{"type":"admonitionTitle","children":[{"type":"text","value":"Important","key":"T7mCJ9K4uS"}],"key":"vrI8kvCKsT"},{"type":"paragraph","position":{"start":{"line":14,"column":1},"end":{"line":14,"column":1}},"children":[{"type":"text","value":"Ce contenu pédagogique est adressé à des étudiant.e.s de deuxième année de licence de Physique dans le cadre d’une offre de formation qui complète les notions abordées dans ce contenu par une seconde unité d’enseignement de troisème année de licence de Physique. Ce contenu n’est ni exhaustif, ni indispensable, ni parfait mais c’est le mien.","position":{"start":{"line":14,"column":1},"end":{"line":14,"column":1}},"key":"yr3AI0CtbF"}],"key":"Oy4EaPsce8"}],"key":"OpmdteSL4Q"},{"type":"paragraph","position":{"start":{"line":18,"column":1},"end":{"line":19,"column":1}},"children":[{"type":"text","value":"Brest, le 7 janvier 2026\nDépartement de Physique","position":{"start":{"line":18,"column":1},"end":{"line":18,"column":1}},"key":"ROXI5vr4Ec"}],"key":"krUKc6rZ4b"},{"type":"paragraph","position":{"start":{"line":21,"column":1},"end":{"line":21,"column":1}},"children":[{"type":"strong","position":{"start":{"line":21,"column":1},"end":{"line":21,"column":1}},"children":[{"type":"text","value":"2025-2026","position":{"start":{"line":21,"column":1},"end":{"line":21,"column":1}},"key":"AdUKpicENm"}],"key":"LCYhyEGPXj"}],"key":"hTC48tvHs3"}],"key":"YmuWjqeaOs"}],"key":"UCSEQiM6va"},"references":{"cite":{"order":[],"data":{}}},"footer":{"navigation":{"next":{"title":"Bibliographie","url":"/bibliocours","group":"Introduction à la mécanique quantique"}}},"domain":"http://localhost:3000"}